targetviz/__init__.py
targetviz/config.py
targetviz/config_default.yaml
targetviz/main.py
targetviz/templates/base.html
targetviz/templates/extra_col.html
targetviz-0.0.1.dist-info/LICENSE
targetviz-0.0.1.dist-info/METADATA
targetviz-0.0.1.dist-info/WHEEL
targetviz-0.0.1.dist-info/top_level.txt
targetviz-0.0.1.dist-info/RECORD
