Metadata-Version: 2.1
Name: targetviz
Version: 0.0.1
Summary: Package for generating automatic reports of variable analyses related to a target variable
Author: Luis de Quadras
License: MIT License
Project-URL: Homepage, https://github.com/dequadras/targetviz
Keywords: targetviz,data analysis,data visualization,data science
Classifier: Development Status :: 3 - Alpha
Classifier: Intended Audience :: Science/Research
Classifier: Topic :: Scientific/Engineering :: Visualization
Classifier: Programming Language :: Python :: 3 :: Only
Classifier: Programming Language :: Python :: 3.8
Requires-Python: >=3.8
License-File: LICENSE
Requires-Dist: confuse
Requires-Dist: jinja2
Requires-Dist: matplotlib>3.3
Requires-Dist: numpy>1.22
Requires-Dist: pandas>1.2
Requires-Dist: scikit-learn>1.0
Requires-Dist: seaborn>0.11
Requires-Dist: importlib-resources; python_version < "3.10"
